redis_wrapped_mkstemp.py
redis_wrapped_mkstemp-1.0.0.dist-info/metadata.json
redis_wrapped_mkstemp-1.0.0.dist-info/METADATA
redis_wrapped_mkstemp-1.0.0.dist-info/RECORD
redis_wrapped_mkstemp-1.0.0.dist-info/DESCRIPTION.rst
redis_wrapped_mkstemp-1.0.0.dist-info/top_level.txt
redis_wrapped_mkstemp-1.0.0.dist-info/WHEEL
