Metadata-Version: 2.0
Name: redis-wrapped-mkstemp
Version: 1.0.0
Summary: redis_wrapped_mkstemp is a utility for generating unique-named files using Redis.
Home-page: https://github.com/rikonor/redis_wrapped_mkstemp
Author: Or Rikon
Author-email: rikonor@gmail.com
License: MIT
Keywords: redis
Platform: UNKNOWN
